htmlemailer/__init__.py
htmlemailer/admin.py
htmlemailer/models.py
htmlemailer/tests.py
htmlemailer/views.py
htmlemailer/migrations/__init__.py
htmlemailer/templates/htmlemailer/boilerplate.html
htmlemailer/templates/htmlemailer/example.html
htmlemailer/templates/htmlemailer/example.txt
htmlemailer/templates/htmlemailer/example_subject.txt
htmlemailer/templates/htmlemailer/example_template.html
htmlemailer/templates/htmlemailer/example_template.txt
django_html_emailer-0.1.0.dist-info/LICENSE
django_html_emailer-0.1.0.dist-info/METADATA
django_html_emailer-0.1.0.dist-info/WHEEL
django_html_emailer-0.1.0.dist-info/top_level.txt
django_html_emailer-0.1.0.dist-info/RECORD
