Metadata-Version: 2.1
Name: django-html-emailer
Version: 0.1.0
Summary: Utility for sending HTML emails from Django.
Home-page: https://github.com/if-then-fund/django-html-emailer
Author: Joshua Tauberer
Author-email: jt@occams.info
License: MIT
Keywords: Django email HTML
Platform: UNKNOWN
Classifier: Intended Audience :: Developers
Classifier: Topic :: Software Development :: Libraries :: Python Modules
Classifier: Programming Language :: Python :: 2
Classifier: Programming Language :: Python :: 2.7
Classifier: Programming Language :: Python :: 3
Classifier: Programming Language :: Python :: 3.4
Classifier: Programming Language :: Python :: 3.5
Classifier: Programming Language :: Python :: 3.6
Requires-Dist: commonmark (>=0.8.0)
Requires-Dist: commonmarkextensions (>=0.0.1)
Requires-Dist: inlinestyler
